PyLucid-3.2.0.data/scripts/pylucid_admin.py
PyLucid-3.2.0.data/scripts/pylucid_boot.py
pylucid/__init__.py
pylucid/admin.py
pylucid/base_settings.py
pylucid/base_urls.py
pylucid/context_processors.py
pylucid/models.py
pylucid/multisite_views.py
pylucid/pylucid_admin.py
pylucid/pylucid_boot.py
pylucid/utils.py
pylucid/version.py
pylucid/admin_shell/__init__.py
pylucid/admin_shell/developer_shell.py
pylucid/admin_shell/normal_shell.py
pylucid/admin_shell/path_helper.py
pylucid/coverage_html/__init___py.html
pylucid/coverage_html/admin_py.html
pylucid/coverage_html/admin_shell___init___py.html
pylucid/coverage_html/admin_shell_developer_shell_py.html
pylucid/coverage_html/admin_shell_normal_shell_py.html
pylucid/coverage_html/admin_shell_path_helper_py.html
pylucid/coverage_html/admin_shell_requirements_py.html
pylucid/coverage_html/base_settings_py.html
pylucid/coverage_html/base_urls_py.html
pylucid/coverage_html/context_processors_py.html
pylucid/coverage_html/coverage_html.js
pylucid/coverage_html/index.html
pylucid/coverage_html/jquery.ba-throttle-debounce.min.js
pylucid/coverage_html/jquery.hotkeys.js
pylucid/coverage_html/jquery.isonscreen.js
pylucid/coverage_html/jquery.min.js
pylucid/coverage_html/jquery.tablesorter.min.js
pylucid/coverage_html/management___init___py.html
pylucid/coverage_html/management_commands___init___py.html
pylucid/coverage_html/management_commands_create_test_pages_py.html
pylucid/coverage_html/management_commands_run_test_project_dev_server_py.html
pylucid/coverage_html/models_py.html
pylucid/coverage_html/multisite_views_py.html
pylucid/coverage_html/pylucid_admin_py.html
pylucid/coverage_html/pylucid_boot_py.html
pylucid/coverage_html/requirements___init___py.html
pylucid/coverage_html/style.css
pylucid/coverage_html/tests___init___py.html
pylucid/coverage_html/tests_settings_py.html
pylucid/coverage_html/tests_test_cms_check_py.html
pylucid/coverage_html/tests_test_cmsplugin_markup_py.html
PyLucid-3.2.0.dist-info/LICENSE
PyLucid-3.2.0.dist-info/METADATA
PyLucid-3.2.0.dist-info/WHEEL
PyLucid-3.2.0.dist-info/entry_points.txt
PyLucid-3.2.0.dist-info/top_level.txt
PyLucid-3.2.0.dist-info/RECORD
