Metadata-Version: 2.1
Name: PyLucid
Version: 3.2.0
Summary: PyLucid CMS
Home-page: http://www.pylucid.org
Author: ['Diemer, Jens', 'Grebs, Christopher', 'Herzog, Manuel', 'Ranta-aho, Perttu']
Author-email: pylucid@jensdiemer.de
Maintainer: Jens Diemer
License: UNKNOWN
Download-URL: http://www.pylucid.org/en/download/
Platform: UNKNOWN
Classifier: Development Status :: 2 - Pre-Alpha
Classifier: Environment :: Web Environment
Classifier: Intended Audience :: Developers
Classifier: License :: OSI Approved :: GNU General Public License (GPL)
Classifier: Programming Language :: Python :: 3.5
Classifier: Programming Language :: Python :: 3.6
Classifier: Programming Language :: Python :: 3.7
Classifier: Programming Language :: Python :: 3 :: Only
Classifier: Framework :: Django
Classifier: Framework :: Django :: 1.11
Classifier: Topic :: Database :: Front-Ends
Classifier: Topic :: Documentation
Classifier: Topic :: Internet :: WWW/HTTP :: Dynamic Content
Classifier: Topic :: Internet :: WWW/HTTP :: Site Management
Classifier: Topic :: Internet :: WWW/HTTP :: WSGI :: Application
Classifier: Operating System :: OS Independent
Requires-Python: >=3.5
Requires-Dist: bootstrap-env (>=1.0.0rc17)
